numcodecs_combinators/__init__.py
numcodecs_combinators/_chunked.py
numcodecs_combinators/abc.py
numcodecs_combinators/best.py
numcodecs_combinators/framed.py
numcodecs_combinators/py.typed
numcodecs_combinators/stack.py
numcodecs_combinators-0.2.13.dist-info/METADATA
numcodecs_combinators-0.2.13.dist-info/WHEEL
numcodecs_combinators-0.2.13.dist-info/entry_points.txt
numcodecs_combinators-0.2.13.dist-info/licenses/LICENSE
numcodecs_combinators-0.2.13.dist-info/RECORD
