Metadata-Version: 2.4
Name: numcodecs-combinators
Version: 0.2.13
Summary: Combinator codecs for the `numcodecs` buffer compression API
License-Expression: MPL-2.0
License-File: LICENSE
Requires-Python: >=3.10
Requires-Dist: leb128~=1.0.8
Requires-Dist: numcodecs<0.17,>=0.13.0
Requires-Dist: numpy~=2.0
Requires-Dist: typing-extensions~=4.6
Provides-Extra: xarray
Requires-Dist: dask>=2024.6; extra == 'xarray'
Requires-Dist: xarray>=2024.06; extra == 'xarray'
